{"13209":{"asistencia_datos":{"-Ok3uGrwprnEqkKgh0B1":{"100530331":true,"100541108":true,"100647487":true,"100671989":true,"100695045":true,"100710476":true,"100725935":true,"100742756":true,"100770078":true,"100773313":true,"100779034":true,"100783611":true}},"asistencias":{"-Ok3uGrwprnEqkKgh0B1":{"fecha":"2026-01-28","id":"-Ok3uGrwprnEqkKgh0B1","nombre":"2026-01-28"}},"encuentros":{"e0":{"aula":"LABORATORIO DE FISICA - SEDE 214","dias":"I","hora":"9:00 AM - 10:50 AM"},"e1":{"aula":"FACULTAD DE INGENIERIA 206","dias":"V","hora":"9:00 AM - 10:50 AM"}},"estudiantes":{"905476":{"id_estudiante":"905476","matricula":"905476","nombre":"Cruz Mancebo, Paulino"},"100065627":{"id_estudiante":"100065627","matricula":"100065627","nombre":"Martinez Tatis, Delvis J."},"100530331":{"id_estudiante":"100530331","matricula":"100530331","nombre":"Rodriguez Sanchez, Emarlyn"},"100541108":{"id_estudiante":"100541108","matricula":"100541108","nombre":"Soriano Quezada, Miguel Angel"},"100588816":{"id_estudiante":"100588816","matricula":"100588816","nombre":"Vallejo, Alberto"},"100609752":{"id_estudiante":"100609752","matricula":"100609752","nombre":"Cruz Santos, Edmil Gilberto"},"100621094":{"id_estudiante":"100621094","matricula":"100621094","nombre":"Tavarez Ramirez, Miguel Emmanuel"},"100647487":{"id_estudiante":"100647487","matricula":"100647487","nombre":"Rosario Diaz, Leandro"},"100671989":{"id_estudiante":"100671989","matricula":"100671989","nombre":"Capellan Guerrero, Dirk Sael"},"100692713":{"id_estudiante":"100692713","matricula":"100692713","nombre":"Borge Perez, Marcos Isai"},"100695045":{"id_estudiante":"100695045","matricula":"100695045","nombre":"Morillo Moreno, Jasleyn"},"100695505":{"id_estudiante":"100695505","matricula":"100695505","nombre":"Santos Javier, Yariel"},"100696078":{"id_estudiante":"100696078","matricula":"100696078","nombre":"Diaz Tavarez, Jose Ismael"},"100710476":{"id_estudiante":"100710476","matricula":"100710476","nombre":"Perez Garcia, Yarlin Serginet"},"100725935":{"id_estudiante":"100725935","matricula":"100725935","nombre":"Benitez Paulino, Betsi Yaira"},"100734087":{"id_estudiante":"100734087","matricula":"100734087","nombre":"Paniagua Bello, Brianny Nicole"},"100742756":{"id_estudiante":"100742756","matricula":"100742756","nombre":"Batista Marte, Ismel Annery"},"100755335":{"id_estudiante":"100755335","matricula":"100755335","nombre":"Rosario Luciano, Deyfri Antonio"},"100768738":{"id_estudiante":"100768738","matricula":"100768738","nombre":"Carrasco Mendez, Ivanny Elizabeth"},"100770078":{"id_estudiante":"100770078","matricula":"100770078","nombre":"Acosta Rodriguez, Camila"},"100773313":{"id_estudiante":"100773313","matricula":"100773313","nombre":"Ureña Alcantara, Xaviel Abad"},"100774966":{"id_estudiante":"100774966","matricula":"100774966","nombre":"Luciano Baez, Karla Beatriz"},"100777506":{"id_estudiante":"100777506","matricula":"100777506","nombre":"Gonzalez, Martin Gabriel"},"100779034":{"id_estudiante":"100779034","matricula":"100779034","nombre":"Braghini Rodriguez, Alessio"},"100783611":{"id_estudiante":"100783611","matricula":"100783611","nombre":"Cheas Valdez, Randy Nelson"},"100792183":{"id_estudiante":"100792183","matricula":"100792183","nombre":"Reyes Almanzar, Sael"},"100793896":{"id_estudiante":"100793896","matricula":"100793896","nombre":"Perez Ovidio, Fernand Arturo"},"100808529":{"id_estudiante":"100808529","matricula":"100808529","nombre":"Segura Tavarez, Emilio Sebastian"},"100808633":{"id_estudiante":"100808633","matricula":"100808633","nombre":"Vicioso De Leon, Yachayra Zachary"},"100809221":{"id_estudiante":"100809221","matricula":"100809221","nombre":"Guzman Mejia, Willian Emilio"},"100809737":{"id_estudiante":"100809737","matricula":"100809737","nombre":"Romero Conde, Jaime Domingo"},"100810778":{"id_estudiante":"100810778","matricula":"100810778","nombre":"Escarraman Reyes, Carlos Andre"}},"evaluaciones":{"-OkcxCpxWBVnAnf60n4O":{"esExtra":1,"id":"-OkcxCpxWBVnAnf60n4O","nombre":"PUNTOS EXTRA","valor":100},"-Om0TQO1uJUF7_IxTegX":{"esExtra":0,"id":"-Om0TQO1uJUF7_IxTegX","nombre":"Práctica suma de vectores","valor":1}},"notas":{"-OkcxCpxWBVnAnf60n4O":{"905476":1,"100671989":2,"100695505":0.5,"100710476":0.5,"100734087":0.5,"100742756":4.5,"100755335":3,"100777506":0.5,"100779034":2.5,"100783611":0.5,"100792183":1.5,"100793896":0.5,"100808633":0.5,"100809221":0.5,"100809737":4.5,"100810778":4.5},"-Om0TQO1uJUF7_IxTegX":{"905476":1,"100541108":1,"100647487":1,"100671989":1,"100695045":1,"100695505":1,"100710476":1,"100725935":1,"100734087":1,"100742756":1,"100770078":1,"100774966":1,"100777506":1,"100779034":1,"100783611":1,"100793896":1,"100808529":1,"100808633":1,"100809221":1,"100809737":1,"100810778":1}}},"13223":{"asistencia_datos":{"-Ol6eQKYIu0Ar7bZwM2j":{"100697178":true,"100775409":true,"100780907":true,"100781946":true,"100789127":true,"100791922":true,"AI5952":true}},"asistencias":{"-Ol6eQKYIu0Ar7bZwM2j":{"fecha":"2026-02-10","id":"-Ol6eQKYIu0Ar7bZwM2j","nombre":"2026-02-10"}},"encuentros":{"e0":{"aula":"CIENCIAS JURIDICAS A 302","dias":"M","hora":"8:00 AM - 9:50 AM"},"e1":{"aula":"EUGENIO MARIA DE HOSTOS 218","dias":"J","hora":"8:00 AM - 9:50 AM"}},"estudiantes":{"100638729":{"id_estudiante":"100638729","matricula":"100638729","nombre":"Santana Batermi, Luis"},"100697178":{"id_estudiante":"100697178","matricula":"100697178","nombre":"Acosta Upia, Dileynis"},"100732400":{"id_estudiante":"100732400","matricula":"100732400","nombre":"Alvarez Medrano, Oderys  Cristina"},"100775409":{"id_estudiante":"100775409","matricula":"100775409","nombre":"Ramirez German, Anaidanis"},"100780907":{"id_estudiante":"100780907","matricula":"100780907","nombre":"De Paula Acosta, Raudy Saul"},"100781946":{"id_estudiante":"100781946","matricula":"100781946","nombre":"Moreno Tellerias, Mayerlis"},"100789127":{"id_estudiante":"100789127","matricula":"100789127","nombre":"Rosado Rosa, Scarlet Mariela"},"100791922":{"id_estudiante":"100791922","matricula":"100791922","nombre":"Ventura Medina, Virginia"},"AI5952":{"id_estudiante":"AI5952","matricula":"AI5952","nombre":"Lora Cuello, Heidy"}},"evaluaciones":{"-OkYfqKchv4ulSuWVrmF":{"esExtra":0,"id":"-OkYfqKchv4ulSuWVrmF","nombre":"Practica suma vectores","valor":1},"-Okhux9Z4JgI4F6NSCz3":{"esExtra":1,"id":"-Okhux9Z4JgI4F6NSCz3","nombre":"PUNTOS EXTRA","valor":100}},"notas":{"-OkYfqKchv4ulSuWVrmF":{"100697178":1,"100732400":1,"100775409":1,"100780907":1,"100781946":1,"100789127":1,"100791922":1,"AI5952":1},"-Okhux9Z4JgI4F6NSCz3":{"100697178":1.5,"100732400":1,"100775409":2.5,"100780907":1.5,"100781946":1,"100789127":0.5,"100791922":3.5}}},"13256":{"encuentros":{"e0":{"aula":"FACULTAD DE INGENIERIA 218","dias":"L","hora":"8:00 AM - 9:50 AM"}},"estudiantes":{"100158545":{"id_estudiante":"100158545","matricula":"100158545","nombre":"Morban Montero, Misael"},"100435366":{"id_estudiante":"100435366","matricula":"100435366","nombre":"Vargas Tejeda, Angel Amable"},"100448587":{"id_estudiante":"100448587","matricula":"100448587","nombre":"Olivares, Raimy Joel"},"100455082":{"id_estudiante":"100455082","matricula":"100455082","nombre":"Zorrilla, Eyfry Miguel"},"100483035":{"id_estudiante":"100483035","matricula":"100483035","nombre":"Ramirez Sierra, Maria Altagracia"},"100485412":{"id_estudiante":"100485412","matricula":"100485412","nombre":"Pinales Diaz, Ana Yris"},"100506035":{"id_estudiante":"100506035","matricula":"100506035","nombre":"Encarnacion Medina, Wander Alexander"},"100515137":{"id_estudiante":"100515137","matricula":"100515137","nombre":"Vizcaino Lara, Lisbeth Ivelisse"},"100515306":{"id_estudiante":"100515306","matricula":"100515306","nombre":"Richardson Moreno, Maximo"},"100606599":{"id_estudiante":"100606599","matricula":"100606599","nombre":"Mateo Sanchez, Alexander"},"100612584":{"id_estudiante":"100612584","matricula":"100612584","nombre":"Guzman Encarnacion, Rohandy"},"100632052":{"id_estudiante":"100632052","matricula":"100632052","nombre":"Nuñez Concepcion, Mayelin Arleti"},"100645004":{"id_estudiante":"100645004","matricula":"100645004","nombre":"Fernandez Matos, Tommy"},"100647859":{"id_estudiante":"100647859","matricula":"100647859","nombre":"Martinez, Yelissa"},"100657412":{"id_estudiante":"100657412","matricula":"100657412","nombre":"Rodriguez Heredia, Frederick"},"100667484":{"id_estudiante":"100667484","matricula":"100667484","nombre":"De La Cruz Salvador, Genelys Melian"},"100698672":{"id_estudiante":"100698672","matricula":"100698672","nombre":"Polanco Vargas, Kelvin Elias"},"100698772":{"id_estudiante":"100698772","matricula":"100698772","nombre":"Rijo Pinales, Madeline Massiel"},"100701061":{"id_estudiante":"100701061","matricula":"100701061","nombre":"Beltre Trinidad, Ramon"},"100711756":{"id_estudiante":"100711756","matricula":"100711756","nombre":"Jhonson Taveras, Miguel Antonio"},"100720151":{"id_estudiante":"100720151","matricula":"100720151","nombre":"Villa Del Rosario, Raylin"},"100733365":{"id_estudiante":"100733365","matricula":"100733365","nombre":"Tafur Maldonado, Juan Andres"},"100737862":{"id_estudiante":"100737862","matricula":"100737862","nombre":"Tejeda Santana, Janahira"},"100752865":{"id_estudiante":"100752865","matricula":"100752865","nombre":"Vasquez Bejaran, Bartolo Jose"},"100768578":{"id_estudiante":"100768578","matricula":"100768578","nombre":"Adames Guzman, Braulio"},"100769766":{"id_estudiante":"100769766","matricula":"100769766","nombre":"Rodriguez Montaño, Abigail"},"100771159":{"id_estudiante":"100771159","matricula":"100771159","nombre":"Martinez Medina, Genesis Nicol"},"100771270":{"id_estudiante":"100771270","matricula":"100771270","nombre":"Mesa Jimenez, Moises Francisco"},"100775407":{"id_estudiante":"100775407","matricula":"100775407","nombre":"Ramirez Benitez, Oscar Lorenzo"},"100780472":{"id_estudiante":"100780472","matricula":"100780472","nombre":"Sánchez Cuello, Gaudy Mahatma"}},"evaluaciones":{"-OkTNywsmQIA2Ya5Ug53":{"esExtra":1,"id":"-OkTNywsmQIA2Ya5Ug53","nombre":"PUNTOS EXTRA","valor":100},"-OnqYfDw65wKVxI3JuHD":{"esExtra":0,"id":"-OnqYfDw65wKVxI3JuHD","nombre":"1er parcial","valor":25}},"notas":{"-OkTNywsmQIA2Ya5Ug53":{"100612584":1,"100752865":0.5,"100768578":1.5}}},"13263":{"asistencia_datos":{"-OkZsCnJurCQ42BhOeAb":{"100086887":true,"100105248":true,"100479356":true,"100480738":true,"100489685":true,"100549044":true,"100552665":true,"100612490":true,"100615041":true,"100615768":true,"100655245":true,"100659894":true,"100670764":true,"100673622":true,"100694674":true,"100696156":true}},"asistencias":{"-OkZsCnJurCQ42BhOeAb":{"fecha":"2026-02-03","id":"-OkZsCnJurCQ42BhOeAb","nombre":"2026-02-03"}},"encuentros":{"e0":{"aula":"FACULTAD DE INGENIERIA 218","dias":"M","hora":"12:00 PM - 3:50 PM"}},"estudiantes":{"100086887":{"id_estudiante":"100086887","matricula":"100086887","nombre":"Garó Féliz, Luís M."},"100105248":{"id_estudiante":"100105248","matricula":"100105248","nombre":"Santos Martinez, Maria C."},"100393556":{"id_estudiante":"100393556","matricula":"100393556","nombre":"Gonzalez Perez, Radeivi"},"100479356":{"id_estudiante":"100479356","matricula":"100479356","nombre":"Gonzalez, Alexander"},"100480738":{"id_estudiante":"100480738","matricula":"100480738","nombre":"Corporan Peña, Ana Karina"},"100489685":{"id_estudiante":"100489685","matricula":"100489685","nombre":"Segura Valdez, Angel Luis"},"100549044":{"id_estudiante":"100549044","matricula":"100549044","nombre":"Perez Perez, Cinthia Yamilet"},"100552665":{"id_estudiante":"100552665","matricula":"100552665","nombre":"Sanchez Mota, Randy Jose"},"100612490":{"id_estudiante":"100612490","matricula":"100612490","nombre":"Cuevas Martinez, Luis Angel"},"100615041":{"id_estudiante":"100615041","matricula":"100615041","nombre":"Moscat Valenzuela, Ruben Jhasser"},"100615768":{"id_estudiante":"100615768","matricula":"100615768","nombre":"Zapata Sanchez, Moises Manuel"},"100631425":{"id_estudiante":"100631425","matricula":"100631425","nombre":"Añazco, Wanda Victoria"},"100655245":{"id_estudiante":"100655245","matricula":"100655245","nombre":"Ramirez Mejia, Angel Alberto"},"100659364":{"id_estudiante":"100659364","matricula":"100659364","nombre":"Portes Montas, Alian"},"100659894":{"id_estudiante":"100659894","matricula":"100659894","nombre":"Bastidas Prieto, Jesus David"},"100670764":{"id_estudiante":"100670764","matricula":"100670764","nombre":"Campusano German, Giodaisa Lilianny"},"100673622":{"id_estudiante":"100673622","matricula":"100673622","nombre":"Rodriguez Gonzalez, Pedro Francisco"},"100694674":{"id_estudiante":"100694674","matricula":"100694674","nombre":"Gomez Santos, Elaine Rachel"},"100696156":{"id_estudiante":"100696156","matricula":"100696156","nombre":"Feliz Silfa, Jeremy Josue"},"100700063":{"id_estudiante":"100700063","matricula":"100700063","nombre":"Jimenez Vasquez, Jose Alberto"}},"evaluaciones":{"-OkZkHmuiOsPCvo4UafM":{"esExtra":1,"id":"-OkZkHmuiOsPCvo4UafM","nombre":"PUNTOS EXTRA","valor":100}},"notas":{"-OkZkHmuiOsPCvo4UafM":{"100086887":0.5,"100105248":1,"100393556":1.5,"100480738":0.5,"100549044":3,"100552665":2.5,"100612490":1,"100615041":2.5,"100615768":1,"100655245":0.5,"100659894":1.5,"100673622":4,"100694674":0.5,"100696156":1.5,"100700063":1.5}}},"13264":{"asistencia_datos":{"-Ok_iPM-pG0AtnmFI2sf":{"100179519":true,"100463989":true,"100465850":true,"100465878":true,"100498595":true,"100506401":true,"100535966":true,"100543153":true,"100564355":true,"100576566":true,"100610935":true,"100623020":true}},"asistencias":{"-Ok_iPM-pG0AtnmFI2sf":{"fecha":"2026-02-03","id":"-Ok_iPM-pG0AtnmFI2sf","nombre":"2026-02-03"}},"encuentros":{"e0":{"aula":"FACULTAD DE INGENIERIA 218","dias":"M","hora":"4:00 PM - 7:50 PM"}},"estudiantes":{"100005988":{"id_estudiante":"100005988","matricula":"100005988","nombre":"Millares Valdez, Ramon"},"100179519":{"id_estudiante":"100179519","matricula":"100179519","nombre":"Disan Berbi, Luniel Gilberto"},"100327184":{"id_estudiante":"100327184","matricula":"100327184","nombre":"Alcantara Corporan, Jimmi Gabriel"},"100338436":{"id_estudiante":"100338436","matricula":"100338436","nombre":"Ramirez Santana, Anny Elizabeth"},"100391434":{"id_estudiante":"100391434","matricula":"100391434","nombre":"Agramonte Garcia, Wilkyn Ramon"},"100429639":{"id_estudiante":"100429639","matricula":"100429639","nombre":"Mendez Santana, Isael Felicito"},"100436469":{"id_estudiante":"100436469","matricula":"100436469","nombre":"Ortiz Mordan, Jose Joel"},"100461889":{"id_estudiante":"100461889","matricula":"100461889","nombre":"Rivera Olivier, Ezequiel"},"100463989":{"id_estudiante":"100463989","matricula":"100463989","nombre":"Brito Matos, Angel Alberto"},"100465850":{"id_estudiante":"100465850","matricula":"100465850","nombre":"Diaz Filpo, Carlos Manuel"},"100465878":{"id_estudiante":"100465878","matricula":"100465878","nombre":"Liranzo De La Rosa, Ana Delia"},"100498595":{"id_estudiante":"100498595","matricula":"100498595","nombre":"Lorenzo Gonzalez, Ajmal Antonio"},"100506401":{"id_estudiante":"100506401","matricula":"100506401","nombre":"Medrano Pinales, Jonaztan"},"100535966":{"id_estudiante":"100535966","matricula":"100535966","nombre":"Bautista Antigua, Randy Jose"},"100543153":{"id_estudiante":"100543153","matricula":"100543153","nombre":"Ramirez Mora, Felix Manuel"},"100564355":{"id_estudiante":"100564355","matricula":"100564355","nombre":"Guerrero Perez, Ismael Antonio"},"100576566":{"id_estudiante":"100576566","matricula":"100576566","nombre":"Melendez Ruiz, Jhosuan"},"100610935":{"id_estudiante":"100610935","matricula":"100610935","nombre":"Williams Parra, Ariony Elmo"},"100623020":{"id_estudiante":"100623020","matricula":"100623020","nombre":"Marte De Los Santos, Jose Carlos"},"100655269":{"id_estudiante":"100655269","matricula":"100655269","nombre":"Reyes Bove, Angelica Maria"}},"evaluaciones":{"-Ok_N_aGdb9FilYYiJ8Q":{"esExtra":1,"id":"-Ok_N_aGdb9FilYYiJ8Q","nombre":"PUNTOS EXTRA","valor":100}},"notas":{"-Ok_N_aGdb9FilYYiJ8Q":{"100179519":0.5,"100391434":4,"100463989":0.5,"100465878":0.5,"100498595":1,"100535966":0.5,"100543153":1.5,"100610935":0.5,"100623020":1.5}}},"18930":{"asistencia_datos":{"-Ok5EfBN0OvulbXd_tWO":{"100239370":true,"100427238":true,"100522620":true,"100583775":true,"100587044":true,"100590273":true,"100603475":true,"100608608":true,"100627600":true,"100631111":true,"100646700":true,"100654833":true,"100657802":true,"100678235":true,"100678699":true,"100695281":true,"100711444":true,"100716519":true,"100740449":true,"100745752":true,"100746222":true,"100778068":true,"100784538":true,"100811224":true,"100812651":true,"100814280":true,"CE4015":true}},"asistencias":{"-Ok5EfBN0OvulbXd_tWO":{"fecha":"2026-01-28","id":"-Ok5EfBN0OvulbXd_tWO","nombre":"2026-01-28"}},"encuentros":{"e0":{"aula":"LABORATORIO DE FISICA - SEDE 204","dias":"I","hora":"4:00 PM - 6:50 PM"}},"estudiantes":{"100228758":{"id_estudiante":"100228758","matricula":"100228758","nombre":"Perez Tejeda, Joan M."},"100231979":{"id_estudiante":"100231979","matricula":"100231979","nombre":"Divison Peguero, Leticia"},"100239370":{"id_estudiante":"100239370","matricula":"100239370","nombre":"Turbides Rodriguez, Jose Miguel"},"100366761":{"id_estudiante":"100366761","matricula":"100366761","nombre":"Alcantara Garcia, Joel Ernesto"},"100388121":{"id_estudiante":"100388121","matricula":"100388121","nombre":"Martinez Charles, Jhon Bryant"},"100396233":{"id_estudiante":"100396233","matricula":"100396233","nombre":"Moreno De Leon, Franklin David"},"100400927":{"id_estudiante":"100400927","matricula":"100400927","nombre":"Liranzo Suero, Balentin"},"100416052":{"id_estudiante":"100416052","matricula":"100416052","nombre":"Mercedes Roa, Anglis Andres"},"100427238":{"id_estudiante":"100427238","matricula":"100427238","nombre":"Rodriguez Leon, Joel"},"100466442":{"id_estudiante":"100466442","matricula":"100466442","nombre":"Cruz Santana, Raul Leonardo"},"100467931":{"id_estudiante":"100467931","matricula":"100467931","nombre":"Jimenez Batista, Dormaris Elizabeth"},"100488874":{"id_estudiante":"100488874","matricula":"100488874","nombre":"Terrero Almonte, Isaac"},"100503714":{"id_estudiante":"100503714","matricula":"100503714","nombre":"Nivar, Argeni"},"100522620":{"id_estudiante":"100522620","matricula":"100522620","nombre":"Duran Cruz, Argenys Arbel"},"100527751":{"id_estudiante":"100527751","matricula":"100527751","nombre":"Lappost Jimenez, Richard Thomas"},"100576623":{"id_estudiante":"100576623","matricula":"100576623","nombre":"Montero Ramon, Clari Ivett"},"100577361":{"id_estudiante":"100577361","matricula":"100577361","nombre":"Amparo Castillo, Oscar Leonel"},"100578292":{"id_estudiante":"100578292","matricula":"100578292","nombre":"Rodriguez Montero, Alejandro"},"100583775":{"id_estudiante":"100583775","matricula":"100583775","nombre":"Vasquez Crisostomo, Stivenson"},"100586357":{"id_estudiante":"100586357","matricula":"100586357","nombre":"Tejeda Matos, Federico"},"100587044":{"id_estudiante":"100587044","matricula":"100587044","nombre":"Carmona Peña, Ramon Estiven"},"100590273":{"id_estudiante":"100590273","matricula":"100590273","nombre":"Encarnacion Soriano, Jesus Moises"},"100603475":{"id_estudiante":"100603475","matricula":"100603475","nombre":"Martinez Paulino, Jose Miguel"},"100608608":{"id_estudiante":"100608608","matricula":"100608608","nombre":"Zabala Ferreira, Manuel Arturo"},"100609781":{"id_estudiante":"100609781","matricula":"100609781","nombre":"Dominguez, Raymundo Antonio"},"100611668":{"id_estudiante":"100611668","matricula":"100611668","nombre":"Garcia Mercedes, Edy Jose"},"100614270":{"id_estudiante":"100614270","matricula":"100614270","nombre":"Cruz Then, Angel Gabriel"},"100627600":{"id_estudiante":"100627600","matricula":"100627600","nombre":"Perez Melo, Junior Enrique"},"100631111":{"id_estudiante":"100631111","matricula":"100631111","nombre":"Lopez Luciano, Jose Joaquin"},"100646700":{"id_estudiante":"100646700","matricula":"100646700","nombre":"Fria, Alexander"},"100654641":{"id_estudiante":"100654641","matricula":"100654641","nombre":"Gil Troncoso, Jeferson"},"100654833":{"id_estudiante":"100654833","matricula":"100654833","nombre":"Lopez Genao, Erick Hipolito"},"100655766":{"id_estudiante":"100655766","matricula":"100655766","nombre":"Brito Reyes, Raidy Raul"},"100657802":{"id_estudiante":"100657802","matricula":"100657802","nombre":"Garcia Villar, Carolin"},"100678235":{"id_estudiante":"100678235","matricula":"100678235","nombre":"Ciprian Hernandez, Anthony Stuart"},"100678495":{"id_estudiante":"100678495","matricula":"100678495","nombre":"Fabian Hernandez, Kendris Antonio"},"100678699":{"id_estudiante":"100678699","matricula":"100678699","nombre":"Guzman Guerrero, Isaias"},"100695281":{"id_estudiante":"100695281","matricula":"100695281","nombre":"Ramos Belen, Jean Carlos"},"100697053":{"id_estudiante":"100697053","matricula":"100697053","nombre":"Taveras Popa, Ashanty Elisa"},"100707008":{"id_estudiante":"100707008","matricula":"100707008","nombre":"Moreno Rodriguez, Alexis"},"100711444":{"id_estudiante":"100711444","matricula":"100711444","nombre":"De Los Santos Vasquez, Brisnelly"},"100716519":{"id_estudiante":"100716519","matricula":"100716519","nombre":"Perez Mora, Daniel J."},"100740449":{"id_estudiante":"100740449","matricula":"100740449","nombre":"Villa Frias, Marcos Antonio"},"100745752":{"id_estudiante":"100745752","matricula":"100745752","nombre":"Bermudez Guerrero, Mickael  De Jesus"},"100746222":{"id_estudiante":"100746222","matricula":"100746222","nombre":"Sanchez Vasquez, Gregori Alejandro Junior"},"100748150":{"id_estudiante":"100748150","matricula":"100748150","nombre":"De La Cruz De Leon, Daniel"},"100757227":{"id_estudiante":"100757227","matricula":"100757227","nombre":"Frias Paula, Melany"},"100773435":{"id_estudiante":"100773435","matricula":"100773435","nombre":"Bautista Rosario, Genesis Sandybel"},"100774260":{"id_estudiante":"100774260","matricula":"100774260","nombre":"Baez Trinidad, Oliver Miguel"},"100778068":{"id_estudiante":"100778068","matricula":"100778068","nombre":"Rodriguez Disla, Sandra"},"100778925":{"id_estudiante":"100778925","matricula":"100778925","nombre":"Tavarez Nuñez, Jose Reilyn"},"100784538":{"id_estudiante":"100784538","matricula":"100784538","nombre":"Palmers Hernandez, Kamel"},"100797123":{"id_estudiante":"100797123","matricula":"100797123","nombre":"Hiciano Lora, Leuri Michael"},"100811224":{"id_estudiante":"100811224","matricula":"100811224","nombre":"Medina Montero, Wander Dioni"},"100812651":{"id_estudiante":"100812651","matricula":"100812651","nombre":"Hernandez Velez, Angel Samuel"},"100814280":{"id_estudiante":"100814280","matricula":"100814280","nombre":"Medina Piña, Leandro Elyhu"},"100815396":{"id_estudiante":"100815396","matricula":"100815396","nombre":"Lagares Reyes, Jhon Junior"},"BA9838":{"id_estudiante":"BA9838","matricula":"BA9838","nombre":"Rickards Muñoz, Nelson"},"CE4015":{"id_estudiante":"CE4015","matricula":"CE4015","nombre":"De Los Santos Medina, Marlenys"},"FA3661":{"id_estudiante":"FA3661","matricula":"FA3661","nombre":"Tavarez Ramos, Albert S."}},"evaluaciones":{"-Ok5GIk48d3cErdBUoYS":{"esExtra":1,"id":"-Ok5GIk48d3cErdBUoYS","nombre":"PUNTOS EXTRA","valor":100}},"notas":{"-Ok5GIk48d3cErdBUoYS":{"100400927":0.5,"100416052":0.5,"100466442":0.5,"100488874":0.5,"100503714":0.5,"100522620":1.5,"100578292":0.5,"100583775":0.5,"100586357":0.5,"100587044":0.5,"100590273":0.5,"100603475":0.5,"100627600":1,"100631111":2,"100654833":1,"100678235":1,"100678495":0.5,"100695281":0.5,"100697053":3,"100707008":0.5,"100711444":0.5,"100745752":1.5,"100748150":1,"100774260":0.5,"100778068":0.5,"100778925":0.5,"100784538":0.5,"100797123":0.5,"100812651":0.5,"FA3661":0.5}}},"20348":{"encuentros":{"e0":{"aula":"EUGENIO MARIA DE HOSTOS 213","dias":"S","hora":"7:00 AM - 9:50 AM"}},"estudiantes":{"100227007":{"id_estudiante":"100227007","matricula":"100227007","nombre":"De Leon Figuereo, Darleny L."},"100231794":{"id_estudiante":"100231794","matricula":"100231794","nombre":"Castaño, Jonathan"},"100236430":{"id_estudiante":"100236430","matricula":"100236430","nombre":"Cruzado Nuñez, Zujeidi"},"100237895":{"id_estudiante":"100237895","matricula":"100237895","nombre":"Mendez Guillen, Hector D."},"100375430":{"id_estudiante":"100375430","matricula":"100375430","nombre":"Mendez Aquino, Alexandra Yamileisy"},"100398842":{"id_estudiante":"100398842","matricula":"100398842","nombre":"Severino Vasquez, Elba Tania"},"100497047":{"id_estudiante":"100497047","matricula":"100497047","nombre":"Perez Guerrero, Darren Adalberto"},"100537691":{"id_estudiante":"100537691","matricula":"100537691","nombre":"De Los Santos De Paula, Luis Eduardo"},"100548851":{"id_estudiante":"100548851","matricula":"100548851","nombre":"Martinez De La Cruz, Moris"},"100581924":{"id_estudiante":"100581924","matricula":"100581924","nombre":"Castillo Frias, Shayra"},"100599024":{"id_estudiante":"100599024","matricula":"100599024","nombre":"Mercedes Lopez, Clary Esther"},"100660012":{"id_estudiante":"100660012","matricula":"100660012","nombre":"Castillo Valerio, Katherine"},"100667964":{"id_estudiante":"100667964","matricula":"100667964","nombre":"Lorenzo Joran, Marieli"},"100673672":{"id_estudiante":"100673672","matricula":"100673672","nombre":"Rosario Calzado, Perla Miguelina"},"100677761":{"id_estudiante":"100677761","matricula":"100677761","nombre":"Araujo Paulino, Luisanna Eduarda"},"100686649":{"id_estudiante":"100686649","matricula":"100686649","nombre":"Beriguete Ramirez, Chairiny"},"100694706":{"id_estudiante":"100694706","matricula":"100694706","nombre":"Guzman, Stalin Danilo"},"100695117":{"id_estudiante":"100695117","matricula":"100695117","nombre":"Oviedo Guzman, Jenifer Arianny"},"100697230":{"id_estudiante":"100697230","matricula":"100697230","nombre":"Almonte Vasquez, Massiel"},"100705933":{"id_estudiante":"100705933","matricula":"100705933","nombre":"Caraballo Ramirez, Jazmin Yamilette"},"100707821":{"id_estudiante":"100707821","matricula":"100707821","nombre":"Minyetty Feliz, Francis Neftali"},"100708151":{"id_estudiante":"100708151","matricula":"100708151","nombre":"Lendorf Reyes, Kismeilin Chanel"},"100727099":{"id_estudiante":"100727099","matricula":"100727099","nombre":"Brito, Maria Cristina"},"100731311":{"id_estudiante":"100731311","matricula":"100731311","nombre":"Benitez Caraballo, Miguel Angel"},"100734974":{"id_estudiante":"100734974","matricula":"100734974","nombre":"Diaz Mota, Miguel Angel"},"100737906":{"id_estudiante":"100737906","matricula":"100737906","nombre":"Valentin De Jesus, Maria Crystal"},"100747986":{"id_estudiante":"100747986","matricula":"100747986","nombre":"Bello Castillo, Eridania"},"100782781":{"id_estudiante":"100782781","matricula":"100782781","nombre":"Montero De Oleo, Lauris"},"100784525":{"id_estudiante":"100784525","matricula":"100784525","nombre":"Nuñez Mejia, Elianna"},"100790290":{"id_estudiante":"100790290","matricula":"100790290","nombre":"De La Rosa Velazquez, Rosabelis"},"100790376":{"id_estudiante":"100790376","matricula":"100790376","nombre":"Medrano Reyes, Maria Dolores"},"100801470":{"id_estudiante":"100801470","matricula":"100801470","nombre":"Paredes Tejeda, Darelin Crisleydis"},"100802078":{"id_estudiante":"100802078","matricula":"100802078","nombre":"Osoria Gonzalez, Vianny Jasmin"},"100802935":{"id_estudiante":"100802935","matricula":"100802935","nombre":"Celeste Samboy, Ana Patricia"},"100810238":{"id_estudiante":"100810238","matricula":"100810238","nombre":"Roa Montero, Mauricia"},"100814832":{"id_estudiante":"100814832","matricula":"100814832","nombre":"Vasquez, Yuleisy Franchesca"},"100816872":{"id_estudiante":"100816872","matricula":"100816872","nombre":"Encarnacion Aquino, Albierys Daniel"},"100820942":{"id_estudiante":"100820942","matricula":"100820942","nombre":"Read Frias, Hillary Miguelina"},"100821205":{"id_estudiante":"100821205","matricula":"100821205","nombre":"Diaz Nivar, Emily Aydeliz"},"100823381":{"id_estudiante":"100823381","matricula":"100823381","nombre":"Mena Mojica, Daniel Henrique"},"100824881":{"id_estudiante":"100824881","matricula":"100824881","nombre":"Herrera Sosa, Isabel"},"100826146":{"id_estudiante":"100826146","matricula":"100826146","nombre":"Rosado Brito, Justin Gabriel"},"100826500":{"id_estudiante":"100826500","matricula":"100826500","nombre":"Hernandez Morel, Yizauris Dahianna"},"100831990":{"id_estudiante":"100831990","matricula":"100831990","nombre":"Mejia Duran, Elia Enmanuel"},"BD3435":{"id_estudiante":"BD3435","matricula":"BD3435","nombre":"Contreras Hidalgo, Dermis"}},"evaluaciones":{"-OkIrOkOuCkaIUCf1jCZ":{"esExtra":1,"id":"-OkIrOkOuCkaIUCf1jCZ","nombre":"PUNTOS EXTRA","valor":100},"-OoFFWLO3ZJDXhQGopJE":{"esExtra":0,"id":"-OoFFWLO3ZJDXhQGopJE","nombre":"Manual parte 1","valor":8}},"notas":{"-OkIrOkOuCkaIUCf1jCZ":{"100497047":0.5,"100537691":0.5,"100581924":0.5,"100660012":3,"100667964":0.5,"100707821":2.5,"100782781":1,"100790376":1,"100801470":0.5,"100810238":0.5,"100823381":0.5,"100831990":3},"-OoFFWLO3ZJDXhQGopJE":{"100537691":5,"100548851":8,"100581924":8,"100667964":7.5,"100707821":8,"100782781":7.5,"100801470":7,"100802935":8,"100810238":7.5,"100821205":7.5}}},"20392":{"encuentros":{"e0":{"aula":"LABORATORIO DE FISICA - SEDE 213","dias":"L","hora":"10:00 AM - 12:50 PM"}},"estudiantes":{"100493020":{"id_estudiante":"100493020","matricula":"100493020","nombre":"Villanueva Payano, Nathaly Maria"},"100507917":{"id_estudiante":"100507917","matricula":"100507917","nombre":"Encarnacion Almanzar, Angelica"},"100569424":{"id_estudiante":"100569424","matricula":"100569424","nombre":"Fabian Lopez, Maria Elena"},"100618605":{"id_estudiante":"100618605","matricula":"100618605","nombre":"Montero Montero, Felicia"},"100650494":{"id_estudiante":"100650494","matricula":"100650494","nombre":"Castillo Concepcion, Claudia Daniela"},"100653690":{"id_estudiante":"100653690","matricula":"100653690","nombre":"Monte De Oca Jaquez, Daniela"},"100670453":{"id_estudiante":"100670453","matricula":"100670453","nombre":"Rodriguez Mesa, Onaiky"},"100679036":{"id_estudiante":"100679036","matricula":"100679036","nombre":"Mejia Ramirez, Henry Javier"},"100689476":{"id_estudiante":"100689476","matricula":"100689476","nombre":"Beltré Martinez, Hayler"},"100703270":{"id_estudiante":"100703270","matricula":"100703270","nombre":"Leonardo Herrera, Dabelis Celines"},"100723837":{"id_estudiante":"100723837","matricula":"100723837","nombre":"Fortuna Bocio, Emeli"},"100728473":{"id_estudiante":"100728473","matricula":"100728473","nombre":"Feliz Valera, Yesica"},"100731041":{"id_estudiante":"100731041","matricula":"100731041","nombre":"Tavarez Santos, Rosmerlin"},"100738887":{"id_estudiante":"100738887","matricula":"100738887","nombre":"Ramirez Veloz, Lorenny"},"100738955":{"id_estudiante":"100738955","matricula":"100738955","nombre":"De Leon Garcia, Angel Gabriel"},"100741992":{"id_estudiante":"100741992","matricula":"100741992","nombre":"Valerio De La Cruz, Naidelyn Esther"},"100746664":{"id_estudiante":"100746664","matricula":"100746664","nombre":"Perez Ventura, Arabelis Antonia"},"100763222":{"id_estudiante":"100763222","matricula":"100763222","nombre":"Figueroa De La Rosa, Elizabeth"},"100763694":{"id_estudiante":"100763694","matricula":"100763694","nombre":"Angulo Elias, Benita"},"100772697":{"id_estudiante":"100772697","matricula":"100772697","nombre":"Herasme Gregorio, Yorsh Gabriel"},"100776716":{"id_estudiante":"100776716","matricula":"100776716","nombre":"Rafael Rafael, Mabel"},"100781073":{"id_estudiante":"100781073","matricula":"100781073","nombre":"Perez Marte, Annie Coral"},"100783621":{"id_estudiante":"100783621","matricula":"100783621","nombre":"Cuevas Carrasco, German Rafael"},"100791430":{"id_estudiante":"100791430","matricula":"100791430","nombre":"Cabral, Soraida"},"100791590":{"id_estudiante":"100791590","matricula":"100791590","nombre":"Garcia Pereyra, Lahioni Belitza"},"100793256":{"id_estudiante":"100793256","matricula":"100793256","nombre":"Perez Ruiz, Luis Manuel"},"100793310":{"id_estudiante":"100793310","matricula":"100793310","nombre":"Salas Rafael, Samuel Isaac"},"100802162":{"id_estudiante":"100802162","matricula":"100802162","nombre":"Baez Morillo, Elianna Esmeralda"},"100803134":{"id_estudiante":"100803134","matricula":"100803134","nombre":"Gonzalez Martinez, Maybelin Chanel"},"100803811":{"id_estudiante":"100803811","matricula":"100803811","nombre":"Sena De La Cruz, Adrian"},"100807696":{"id_estudiante":"100807696","matricula":"100807696","nombre":"Comas Peña, Yullian Gabriella"},"100808548":{"id_estudiante":"100808548","matricula":"100808548","nombre":"Soriano Feliz, Perla Rubi"},"100808732":{"id_estudiante":"100808732","matricula":"100808732","nombre":"Alcantara Hernandez, Damaris"},"100810178":{"id_estudiante":"100810178","matricula":"100810178","nombre":"Matos Urbaez, Marjiorie Cristal"},"100811389":{"id_estudiante":"100811389","matricula":"100811389","nombre":"Otaño Puello, Yefrany"},"100811576":{"id_estudiante":"100811576","matricula":"100811576","nombre":"Rincon Herrera, Majourie Sharline"},"100813359":{"id_estudiante":"100813359","matricula":"100813359","nombre":"Santana Peguero, Yerabelis"},"100813524":{"id_estudiante":"100813524","matricula":"100813524","nombre":"Vasquez De La Cruz, Eliandy Elizabeth"},"100817889":{"id_estudiante":"100817889","matricula":"100817889","nombre":"De Oleo De Oleo, Laura Marina"},"100818072":{"id_estudiante":"100818072","matricula":"100818072","nombre":"Quiñones Kranwinkel, Judit Del Carmen"},"100818073":{"id_estudiante":"100818073","matricula":"100818073","nombre":"Quiñones Kranwinkel, Sarah Esther"},"100820367":{"id_estudiante":"100820367","matricula":"100820367","nombre":"Sanchez Calderon, Mario Antonio"},"100822847":{"id_estudiante":"100822847","matricula":"100822847","nombre":"Martinez Rojas, Juan Carlos"},"100824290":{"id_estudiante":"100824290","matricula":"100824290","nombre":"Reyes Ogando, Jeissys Joshefina"},"100824601":{"id_estudiante":"100824601","matricula":"100824601","nombre":"Castillo De La Cruz, Dania Franchelis"}},"evaluaciones":{"-Onr2z7MJUyfNeHfnBRO":{"esExtra":0,"id":"-Onr2z7MJUyfNeHfnBRO","nombre":"Manual parte 1","valor":8},"-OoRtClxVU4w-2GEj7QW":{"esExtra":1,"id":"-OoRtClxVU4w-2GEj7QW","nombre":"PUNTOS EXTRA","valor":100},"-OoRtJVvoRB2uMEjdtR9":{"esExtra":0,"id":"-OoRtJVvoRB2uMEjdtR9","nombre":"1er parcial","valor":25}},"historial_dictados":{"-OoRtJVvoRB2uMEjdtR9":{"2026-03-23T23-12-43-726Z":{"100569424":1,"100618605":2,"100650494":11,"100689476":4,"100703270":5,"100728473":8.5,"100738955":17.5,"100746664":6,"100763694":5,"100772697":6.5,"100776716":6.5,"100781073":5,"100791590":14,"100793256":3,"100803811":2,"100808548":10,"100808732":0,"100810178":15,"100811389":18,"100813359":1,"100817889":9,"100818072":18,"100818073":9.5,"100822847":16,"100824290":15.5,"100824601":4}}},"notas":{"-Onr2z7MJUyfNeHfnBRO":{"100569424":8,"100618605":6,"100650494":8,"100689476":4.5,"100703270":8,"100728473":8,"100731041":8,"100738955":6.5,"100746664":8,"100763694":8,"100772697":8,"100776716":8,"100781073":8,"100791590":6,"100793256":8,"100808548":8,"100808732":8,"100810178":8,"100811389":8,"100813359":8,"100817889":8,"100818072":8,"100818073":8,"100822847":8,"100824290":8,"100824601":8},"-OoRtJVvoRB2uMEjdtR9":{"100569424":1,"100618605":2,"100650494":11,"100689476":4,"100703270":5,"100728473":8.5,"100738955":17.5,"100746664":6,"100763694":5,"100772697":6.5,"100776716":6.5,"100781073":5,"100791590":14,"100793256":3,"100803811":2,"100808548":10,"100808732":0,"100810178":15,"100811389":18,"100813359":1,"100817889":9,"100818072":18,"100818073":9.5,"100822847":16,"100824290":15.5,"100824601":4}}},"20460":{"asistencia_datos":{"-OkGS3BOcdhhJR8BJfaB":{"100189845":true,"100614069":true,"100640195":true,"100653696":true,"100751113":true,"100779161":true,"100795358":true,"100802917":true,"100809777":true,"100822771":true,"CE9119":true}},"asistencias":{"-OkGS3BOcdhhJR8BJfaB":{"fecha":"2026-01-30","id":"-OkGS3BOcdhhJR8BJfaB","nombre":"2026-01-30"}},"encuentros":{"e0":{"aula":"EUGENIO MARIA DE HOSTOS 107","dias":"V","hora":"7:00 PM - 9:50 PM"}},"estudiantes":{"100189845":{"id_estudiante":"100189845","matricula":"100189845","nombre":"Herrera Ureña, Miguel A."},"100366363":{"id_estudiante":"100366363","matricula":"100366363","nombre":"Pantaleon, Ivelisse"},"100368401":{"id_estudiante":"100368401","matricula":"100368401","nombre":"Santana Gonzalez, Esmeralda"},"100379752":{"id_estudiante":"100379752","matricula":"100379752","nombre":"Botier Brito, Darlin Junior"},"100411464":{"id_estudiante":"100411464","matricula":"100411464","nombre":"Fernandez, Mariel"},"100491375":{"id_estudiante":"100491375","matricula":"100491375","nombre":"Rodriguez Vasquez, Maxiovely Altagracia"},"100500738":{"id_estudiante":"100500738","matricula":"100500738","nombre":"Figuereo, Pamela"},"100515360":{"id_estudiante":"100515360","matricula":"100515360","nombre":"Figuereo De Oleo, Alexander Ernesto"},"100527496":{"id_estudiante":"100527496","matricula":"100527496","nombre":"Echavarria Reyes, Larisbel"},"100592922":{"id_estudiante":"100592922","matricula":"100592922","nombre":"Diaz De Regla, Loiselena"},"100595071":{"id_estudiante":"100595071","matricula":"100595071","nombre":"Ramirez Mendez, Manuela"},"100603533":{"id_estudiante":"100603533","matricula":"100603533","nombre":"Mercedes Feliz, Hingel Antonio"},"100614069":{"id_estudiante":"100614069","matricula":"100614069","nombre":"Beltre Del Carmen, Miriam"},"100626671":{"id_estudiante":"100626671","matricula":"100626671","nombre":"Ferrer Figueroa, Endri Altagracio"},"100640195":{"id_estudiante":"100640195","matricula":"100640195","nombre":"Feliz Peña, Yanna Cristina"},"100653696":{"id_estudiante":"100653696","matricula":"100653696","nombre":"Montilla Landa, Rafael David"},"100656025":{"id_estudiante":"100656025","matricula":"100656025","nombre":"Figuereo Castro, Cristy Daihana"},"100660491":{"id_estudiante":"100660491","matricula":"100660491","nombre":"Gonzalez De Los Santos, Jairon Augusto"},"100690189":{"id_estudiante":"100690189","matricula":"100690189","nombre":"Rivera Perez, Michael Alberto"},"100715097":{"id_estudiante":"100715097","matricula":"100715097","nombre":"Vicioso Amador, Brailing Eduardo"},"100721557":{"id_estudiante":"100721557","matricula":"100721557","nombre":"Diaz Alvarez, Edry Jael"},"100742065":{"id_estudiante":"100742065","matricula":"100742065","nombre":"Arias Cruz, Maria Alejandra"},"100742961":{"id_estudiante":"100742961","matricula":"100742961","nombre":"Greenaway Alvarez, Bawny Naomy"},"100743267":{"id_estudiante":"100743267","matricula":"100743267","nombre":"Suero Brito, Vanessa"},"100743521":{"id_estudiante":"100743521","matricula":"100743521","nombre":"Beltre De Leon, Meriley Cristhin"},"100751113":{"id_estudiante":"100751113","matricula":"100751113","nombre":"Jimenez Lopez, Lorena Giselle"},"100757198":{"id_estudiante":"100757198","matricula":"100757198","nombre":"Doñe, Gleiny"},"100765728":{"id_estudiante":"100765728","matricula":"100765728","nombre":"Lima Nuñez, Nayelis Mabel"},"100771277":{"id_estudiante":"100771277","matricula":"100771277","nombre":"Mojica Peña, Pedro Antonio"},"100779161":{"id_estudiante":"100779161","matricula":"100779161","nombre":"Fernandez Brito, Jerinet Jerelin"},"100782306":{"id_estudiante":"100782306","matricula":"100782306","nombre":"Jimenez Santana, Maria Elena"},"100789326":{"id_estudiante":"100789326","matricula":"100789326","nombre":"Acevedo Remigio, Arianna Gabriela"},"100795358":{"id_estudiante":"100795358","matricula":"100795358","nombre":"Mañon Figueroa, Maria Adelaida"},"100802917":{"id_estudiante":"100802917","matricula":"100802917","nombre":"Beato Batista, Jessica"},"100804707":{"id_estudiante":"100804707","matricula":"100804707","nombre":"Mateo Santana, Rosibel"},"100809777":{"id_estudiante":"100809777","matricula":"100809777","nombre":"Salomon Rodriguez, Luisanna Maria"},"100810735":{"id_estudiante":"100810735","matricula":"100810735","nombre":"Diaz Matias, Franchesca"},"100822723":{"id_estudiante":"100822723","matricula":"100822723","nombre":"Valenzuela Sanchez, Ashly"},"100822771":{"id_estudiante":"100822771","matricula":"100822771","nombre":"Castro Alcantara, Wilmeiris Yaderkis"},"100830625":{"id_estudiante":"100830625","matricula":"100830625","nombre":"Martinez Gonzalez, Katherin Nicole"},"CE9119":{"id_estudiante":"CE9119","matricula":"CE9119","nombre":"Castro Hernandez, Agustina"},"FP1289":{"id_estudiante":"FP1289","matricula":"FP1289","nombre":"Feliz Montero, Ambar"}},"evaluaciones":{"-OkG9OOrfjWQZP3HevCV":{"esExtra":1,"id":"-OkG9OOrfjWQZP3HevCV","nombre":"PUNTOS EXTRA","valor":100},"-OoCVmv8WKOnNgonLpT2":{"esExtra":0,"id":"-OoCVmv8WKOnNgonLpT2","nombre":"Manual parte 1","valor":8}},"notas":{"-OkG9OOrfjWQZP3HevCV":{"100491375":1.5,"100527496":0.5,"100614069":1,"100640195":1,"100653696":1.5,"100715097":1,"100721557":0.5,"100742065":2,"100751113":0.5,"100779161":0.5,"100789326":2,"100795358":0.5,"100802917":1,"CE9119":2,"FP1289":0.5},"-OoCVmv8WKOnNgonLpT2":{"100491375":7.5,"100527496":8,"100595071":8,"100626671":7,"100721557":4.5,"100742065":8,"100742961":8,"100765728":8,"100779161":4,"100789326":4.5,"100802917":8,"100822771":7.5,"100830625":7,"CE9119":8}}},"20759":{"asistencia_datos":{"-OlI3ZwAtpiVqSZlPMjJ":{"100530166":true,"100627210":true,"100745172":true,"100780980":true,"100781073":true,"100787377":true,"100793321":true,"100806424":true,"100811193":true,"100812781":true,"100819440":true,"100820570":true,"100821467":true,"100821975":true,"100822166":true,"100830640":true,"100830920":true}},"asistencias":{"-OlI3ZwAtpiVqSZlPMjJ":{"fecha":"2026-02-12","id":"-OlI3ZwAtpiVqSZlPMjJ","nombre":"2026-02-12"}},"encuentros":{"e0":{"aula":"LABORATORIO DE FISICA - SEDE 203","dias":"J","hora":"1:00 PM - 3:50 PM"}},"estudiantes":{"100530166":{"id_estudiante":"100530166","matricula":"100530166","nombre":"Lorenzo Guerra, Julio"},"100588455":{"id_estudiante":"100588455","matricula":"100588455","nombre":"Minaya Brito, Luzcapril Aledxa"},"100589348":{"id_estudiante":"100589348","matricula":"100589348","nombre":"Martinez Morales, Morelia"},"100624220":{"id_estudiante":"100624220","matricula":"100624220","nombre":"Veloz Vargas, Jesus Alexander"},"100627210":{"id_estudiante":"100627210","matricula":"100627210","nombre":"Troncoso De Jesus, Bellinette"},"100709069":{"id_estudiante":"100709069","matricula":"100709069","nombre":"Diaz Peña, Ruth Esther"},"100724256":{"id_estudiante":"100724256","matricula":"100724256","nombre":"De La Rosa Ramirez, Erickrendry"},"100724383":{"id_estudiante":"100724383","matricula":"100724383","nombre":"Peguero Alcantara, Freddy Emmanuel"},"100736298":{"id_estudiante":"100736298","matricula":"100736298","nombre":"Ubiera Beltran, Ami Maria"},"100745172":{"id_estudiante":"100745172","matricula":"100745172","nombre":"Eusebio, Angela Minerva"},"100763870":{"id_estudiante":"100763870","matricula":"100763870","nombre":"Rodriguez Nivar, Alexandra"},"100779486":{"id_estudiante":"100779486","matricula":"100779486","nombre":"Almonte         Miguel, Francisca"},"100780980":{"id_estudiante":"100780980","matricula":"100780980","nombre":"Jorge Rosario, Josephine Marie"},"100781073":{"id_estudiante":"100781073","matricula":"100781073","nombre":"Perez Marte, Annie Coral"},"100785367":{"id_estudiante":"100785367","matricula":"100785367","nombre":"Cruz De Jesus, Carolina"},"100787376":{"id_estudiante":"100787376","matricula":"100787376","nombre":"Fernandez Luis, Isaac Isidro"},"100787377":{"id_estudiante":"100787377","matricula":"100787377","nombre":"Fernandez Reyes, Anderson Miguel"},"100793321":{"id_estudiante":"100793321","matricula":"100793321","nombre":"Santana, Johana"},"100806424":{"id_estudiante":"100806424","matricula":"100806424","nombre":"Garcia Pujols, Disleimy Arianny"},"100811193":{"id_estudiante":"100811193","matricula":"100811193","nombre":"Mateo Mojica, Ivan Miguel"},"100812781":{"id_estudiante":"100812781","matricula":"100812781","nombre":"Marte Pierre, Juan Pablo"},"100813724":{"id_estudiante":"100813724","matricula":"100813724","nombre":"Cabrera Casilla, Alisson Maricelis"},"100819440":{"id_estudiante":"100819440","matricula":"100819440","nombre":"Sanchez, Alanna Zamira"},"100820239":{"id_estudiante":"100820239","matricula":"100820239","nombre":"Peña Bouchette, Imairoby"},"100820570":{"id_estudiante":"100820570","matricula":"100820570","nombre":"Betances De Los Santos, Nissi"},"100821467":{"id_estudiante":"100821467","matricula":"100821467","nombre":"Perez Liberato, Alina Esmeralda"},"100821975":{"id_estudiante":"100821975","matricula":"100821975","nombre":"Mora Gomez, Arianny Abigail"},"100822166":{"id_estudiante":"100822166","matricula":"100822166","nombre":"Valdez Ramirez, Branly Samil"},"100830640":{"id_estudiante":"100830640","matricula":"100830640","nombre":"Medina Gonzalez, Yocarlin"},"100830920":{"id_estudiante":"100830920","matricula":"100830920","nombre":"Silverio, Katherine Michell"}},"evaluaciones":{"-Omz9WMtfOSC_3DKo_P2":{"esExtra":0,"id":"-Omz9WMtfOSC_3DKo_P2","nombre":"1er parcial","valor":20},"-Oo6aNizaOudf1QVaroU":{"esExtra":0,"id":"-Oo6aNizaOudf1QVaroU","nombre":"2do parcial","valor":20}},"notas":{"-Omz9WMtfOSC_3DKo_P2":{"100530166":7,"100624220":4,"100745172":9.5,"100780980":7,"100781073":5.5,"100787376":4.5,"100787377":6.5,"100793321":2,"100806424":6.5,"100811193":17.5,"100812781":9,"100813724":9,"100819440":8,"100820570":6.5,"100821467":15,"100821975":12,"100822166":6.5,"100830640":4,"100830920":8},"-Oo6aNizaOudf1QVaroU":{"100530166":8.5,"100624220":9,"100780980":12,"100781073":9,"100787376":10,"100787377":11,"100793321":6,"100806424":13,"100811193":9,"100812781":9,"100813724":8,"100819440":13.5,"100820570":11,"100821467":15,"100821975":13,"100822166":10,"100830640":4,"100830920":7.5}}},"26127":{"encuentros":{"e0":{"aula":"LABORATORIO DE FISICA - SEDE 201","dias":"J","hora":"7:00 PM - 9:50 PM"}},"estudiantes":{"100304915":{"id_estudiante":"100304915","matricula":"100304915","nombre":"Fortunato Brand, Jenifer"},"100337899":{"id_estudiante":"100337899","matricula":"100337899","nombre":"Polanco Garcia, Keiri Virginia"},"100412587":{"id_estudiante":"100412587","matricula":"100412587","nombre":"Severino Rojas, Jorge Leuris"},"100416944":{"id_estudiante":"100416944","matricula":"100416944","nombre":"Perez, Yulissa Yanet"},"100457471":{"id_estudiante":"100457471","matricula":"100457471","nombre":"Lora Martinez, Lisbet Maria"},"100479476":{"id_estudiante":"100479476","matricula":"100479476","nombre":"Marte Columna, Florangel Lissette"},"100491655":{"id_estudiante":"100491655","matricula":"100491655","nombre":"Balbuena Hernandez, Leonel"},"100505362":{"id_estudiante":"100505362","matricula":"100505362","nombre":"Pacheco, Ana Delia"},"100538767":{"id_estudiante":"100538767","matricula":"100538767","nombre":"Martinez Fabian, Samuel"},"100550889":{"id_estudiante":"100550889","matricula":"100550889","nombre":"Cabrera Rosario, Rafaela"},"100580822":{"id_estudiante":"100580822","matricula":"100580822","nombre":"Almonte Peña, Rayfer"},"100581011":{"id_estudiante":"100581011","matricula":"100581011","nombre":"Florentino Romero, Alexandra"},"100627528":{"id_estudiante":"100627528","matricula":"100627528","nombre":"Mejia Lorenzo, Victor Manuel"},"100628879":{"id_estudiante":"100628879","matricula":"100628879","nombre":"Marte Amparo, Jose Manuel"},"100719050":{"id_estudiante":"100719050","matricula":"100719050","nombre":"Germes Rodriguez, Natasha Marie"},"100719648":{"id_estudiante":"100719648","matricula":"100719648","nombre":"De Leon Aristy, Jose Manuel"},"100727083":{"id_estudiante":"100727083","matricula":"100727083","nombre":"Bautista Castillo, Natalia"},"100730469":{"id_estudiante":"100730469","matricula":"100730469","nombre":"Gonzalez De Los Santos, Valery Franchesca"},"100763595":{"id_estudiante":"100763595","matricula":"100763595","nombre":"Rodriguez Silvestre, Samil Jose"},"100766947":{"id_estudiante":"100766947","matricula":"100766947","nombre":"Ortiz Castro, Eddileysi"},"100772449":{"id_estudiante":"100772449","matricula":"100772449","nombre":"De La Cruz Villar, Fradelin"},"100777316":{"id_estudiante":"100777316","matricula":"100777316","nombre":"De Los Santos Bueno, Kirsairy Marie"},"100791665":{"id_estudiante":"100791665","matricula":"100791665","nombre":"Martinez De La Cruz, Jannibel"},"100806634":{"id_estudiante":"100806634","matricula":"100806634","nombre":"Roa Encarnacion, Ana Luisa"},"100807025":{"id_estudiante":"100807025","matricula":"100807025","nombre":"Jimenez Ramirez, Elias Xavier"},"100809508":{"id_estudiante":"100809508","matricula":"100809508","nombre":"Nuñez Peña, Maria Jose"},"100810227":{"id_estudiante":"100810227","matricula":"100810227","nombre":"Ramos, Julia Amelia"},"100811121":{"id_estudiante":"100811121","matricula":"100811121","nombre":"Lopez Santos, Mia Vianelys"},"100831275":{"id_estudiante":"100831275","matricula":"100831275","nombre":"Fuentes, Martha Lucia"},"CA3486":{"id_estudiante":"CA3486","matricula":"CA3486","nombre":"Del Carmen Perez, Marianela"}},"evaluaciones":{"-OkB38vMs4UkY5GTAEyV":{"esExtra":1,"id":"-OkB38vMs4UkY5GTAEyV","nombre":"PUNTOS EXTRA","valor":100},"-Oo7R6nF2IUANj9BkBau":{"esExtra":0,"id":"-Oo7R6nF2IUANj9BkBau","nombre":"Manual parte 1","valor":8}},"notas":{"-OkB38vMs4UkY5GTAEyV":{"100479476":1,"100491655":0.5,"100581011":0.5,"100730469":2.5,"100777316":4.5,"100807025":5,"100831275":0.5},"-Oo7R6nF2IUANj9BkBau":{"100479476":8,"100581011":1,"100766947":1,"100777316":7.5,"100807025":4,"100831275":5}}},"30895":{"encuentros":{"e0":{"aula":"FACULTAD DE INGENIERIA 216","dias":"M","hora":"10:00 AM - 11:50 AM"}},"estudiantes":{"100156034":{"id_estudiante":"100156034","matricula":"100156034","nombre":"Rodriguez Alcantara, Ana M."},"100344419":{"id_estudiante":"100344419","matricula":"100344419","nombre":"Montero Montero, Beris"},"100574961":{"id_estudiante":"100574961","matricula":"100574961","nombre":"Placencio De Jesus, Francis Alberto"},"100595647":{"id_estudiante":"100595647","matricula":"100595647","nombre":"Bugue Aragonez, Francheska"},"100629006":{"id_estudiante":"100629006","matricula":"100629006","nombre":"Rodriguez Nivar, Efraulyn Adrian"},"100645664":{"id_estudiante":"100645664","matricula":"100645664","nombre":"Santana Montero, Erica"},"100651279":{"id_estudiante":"100651279","matricula":"100651279","nombre":"Mancebo Urbaez, Alejandro Ignacio"},"100653911":{"id_estudiante":"100653911","matricula":"100653911","nombre":"Ruiz Suero, Angel Elias"},"100655712":{"id_estudiante":"100655712","matricula":"100655712","nombre":"Aybar Vargas, Willy"},"100667887":{"id_estudiante":"100667887","matricula":"100667887","nombre":"Feliz Cruz, Angel Jose Rafael"},"100671312":{"id_estudiante":"100671312","matricula":"100671312","nombre":"Ogando, Alexander Emilio"},"100674288":{"id_estudiante":"100674288","matricula":"100674288","nombre":"Calderon Dominguez, Keraly"},"100675185":{"id_estudiante":"100675185","matricula":"100675185","nombre":"Salas Santos, Jose Florentino"},"100681036":{"id_estudiante":"100681036","matricula":"100681036","nombre":"Grullon Rosario, Mariel"},"100687452":{"id_estudiante":"100687452","matricula":"100687452","nombre":"Rubio Terrero, Meriangel Amelia"},"100692510":{"id_estudiante":"100692510","matricula":"100692510","nombre":"Romero, Jeimi"},"100692713":{"id_estudiante":"100692713","matricula":"100692713","nombre":"Borge Perez, Marcos Isai"},"100694528":{"id_estudiante":"100694528","matricula":"100694528","nombre":"Feliz Mendez, Luis Emmanuel"},"100696078":{"id_estudiante":"100696078","matricula":"100696078","nombre":"Diaz Tavarez, Jose Ismael"},"100696906":{"id_estudiante":"100696906","matricula":"100696906","nombre":"Rosario Contreras, Sulanny"},"100701426":{"id_estudiante":"100701426","matricula":"100701426","nombre":"Jimenez Zapata, Ilexis"},"100702649":{"id_estudiante":"100702649","matricula":"100702649","nombre":"Matos Bello, Amy Marianny"},"100707867":{"id_estudiante":"100707867","matricula":"100707867","nombre":"Perez De Leon, Armando"},"100709363":{"id_estudiante":"100709363","matricula":"100709363","nombre":"Aquino Quezada, Jonathan Bienvenido"},"100734783":{"id_estudiante":"100734783","matricula":"100734783","nombre":"Civil De Los Santos, Julian De Jesus"},"100736153":{"id_estudiante":"100736153","matricula":"100736153","nombre":"Santana De La Cruz, Estefany"},"100743245":{"id_estudiante":"100743245","matricula":"100743245","nombre":"Santana Mota, Cristal"},"100745082":{"id_estudiante":"100745082","matricula":"100745082","nombre":"Cueto Samboy, Moises Jerroon"},"100777116":{"id_estudiante":"100777116","matricula":"100777116","nombre":"Baez Pimentel, Eliezer"},"100808529":{"id_estudiante":"100808529","matricula":"100808529","nombre":"Segura Tavarez, Emilio Sebastian"},"100810778":{"id_estudiante":"100810778","matricula":"100810778","nombre":"Escarraman Reyes, Carlos Andre"},"100811238":{"id_estudiante":"100811238","matricula":"100811238","nombre":"Mejia Hubiere, Juan Luis"},"100817034":{"id_estudiante":"100817034","matricula":"100817034","nombre":"Potenza Espinel, Christian Leonel"},"DE7888":{"id_estudiante":"DE7888","matricula":"DE7888","nombre":"Nuñez G, Fernando"}},"evaluaciones":{"-OmoDNt5Ujvs_UQMgdk7":{"esExtra":1,"id":"-OmoDNt5Ujvs_UQMgdk7","nombre":"PUNTOS EXTRA","valor":100}},"notas":{"-OmoDNt5Ujvs_UQMgdk7":{"100574961":0.5,"100655712":0.5,"100692510":0.5,"100692713":0.5,"100696078":1,"100701426":1,"100707867":0.5,"100709363":0.5,"100808529":0.5}}},"32546":{"encuentros":{"e0":{"aula":"NUEVA UNIVERSIDAD 205","dias":"J","hora":"10:00 AM - 12:50 PM"}},"estudiantes":{"100167064":{"id_estudiante":"100167064","matricula":"100167064","nombre":"Ortiz Reyes, Jose C."},"100297073":{"id_estudiante":"100297073","matricula":"100297073","nombre":"Valdez Ortiz, Yessenia"},"100307602":{"id_estudiante":"100307602","matricula":"100307602","nombre":"Diaz Leon, Alicia"},"100420958":{"id_estudiante":"100420958","matricula":"100420958","nombre":"Nuñez Duran, Luis Miguel"},"100422180":{"id_estudiante":"100422180","matricula":"100422180","nombre":"Roble Contreras, Erinerka"},"100549396":{"id_estudiante":"100549396","matricula":"100549396","nombre":"Garcia Gonzalez, Nelly"},"100582172":{"id_estudiante":"100582172","matricula":"100582172","nombre":"Ricardo Pineda, Debora Maria"},"100588549":{"id_estudiante":"100588549","matricula":"100588549","nombre":"Perez, Carolay Esmeralda"},"100600255":{"id_estudiante":"100600255","matricula":"100600255","nombre":"Almarante Mambru, Bellezely"},"100608514":{"id_estudiante":"100608514","matricula":"100608514","nombre":"Vasquez Bussi, Leslie Michelle"},"100613511":{"id_estudiante":"100613511","matricula":"100613511","nombre":"Feliz Florentino, Javier David"},"100639200":{"id_estudiante":"100639200","matricula":"100639200","nombre":"Feliz Zabala, Thalia Desiree"},"100642588":{"id_estudiante":"100642588","matricula":"100642588","nombre":"Nuñez Mendoza, Franni Nicolle"},"100684030":{"id_estudiante":"100684030","matricula":"100684030","nombre":"Huang Ng, Sandy Wei Shang"},"100698796":{"id_estudiante":"100698796","matricula":"100698796","nombre":"Rodriguez Canario, Ambar Zahori"},"100719477":{"id_estudiante":"100719477","matricula":"100719477","nombre":"Valera Arredondo, Geuris"},"100719914":{"id_estudiante":"100719914","matricula":"100719914","nombre":"Mota Ramirez, Yesenia"},"100746433":{"id_estudiante":"100746433","matricula":"100746433","nombre":"Espinosa Mendez, Joctan Eloim"},"100747154":{"id_estudiante":"100747154","matricula":"100747154","nombre":"De Leon Mendez, Maria Mercedes"},"100750864":{"id_estudiante":"100750864","matricula":"100750864","nombre":"Duran Valerio, Miranda"},"100756188":{"id_estudiante":"100756188","matricula":"100756188","nombre":"Gomez Castro, Marianny"},"100763031":{"id_estudiante":"100763031","matricula":"100763031","nombre":"Perez Mota, Camila"},"100783066":{"id_estudiante":"100783066","matricula":"100783066","nombre":"Del Orbe De Los Santos, Arianna"},"100790100":{"id_estudiante":"100790100","matricula":"100790100","nombre":"Melendez Marrero, Elizabeth"},"100800304":{"id_estudiante":"100800304","matricula":"100800304","nombre":"Suriel Del Rosario, Rosmery"},"100803815":{"id_estudiante":"100803815","matricula":"100803815","nombre":"Sosa  Matos, Karla   Esther"},"100807586":{"id_estudiante":"100807586","matricula":"100807586","nombre":"Bautista Calderon, Elianna Elizabeth"},"100808128":{"id_estudiante":"100808128","matricula":"100808128","nombre":"Mateo Custodio, Dinanyi"},"100808575":{"id_estudiante":"100808575","matricula":"100808575","nombre":"Tejeda Suazo, Breidy Enmanuel"},"100810270":{"id_estudiante":"100810270","matricula":"100810270","nombre":"Sanquintin Peguero, Jerlin Andres"},"100812085":{"id_estudiante":"100812085","matricula":"100812085","nombre":"Batista Espiritu, Yeandry Raymery"},"100812139":{"id_estudiante":"100812139","matricula":"100812139","nombre":"Burgos Garcia, Yaniel Esmil"},"100817106":{"id_estudiante":"100817106","matricula":"100817106","nombre":"Vargas Nival, Eliza"},"100817878":{"id_estudiante":"100817878","matricula":"100817878","nombre":"Cuevas Matos, Eunice Marolina"},"100818029":{"id_estudiante":"100818029","matricula":"100818029","nombre":"Novas Novas, Emely Vileissi"},"100818301":{"id_estudiante":"100818301","matricula":"100818301","nombre":"Cespedes Silfa, Yerenis Trinidad"},"100818304":{"id_estudiante":"100818304","matricula":"100818304","nombre":"Chevalier Peralta, Ashly Elianny"},"100818935":{"id_estudiante":"100818935","matricula":"100818935","nombre":"Cuevas Familia, Yael Alexander"},"100818944":{"id_estudiante":"100818944","matricula":"100818944","nombre":"De La Rosa Casado, Melany Marianny"},"100819002":{"id_estudiante":"100819002","matricula":"100819002","nombre":"Novas Volquez, Joelainis Ana Delis"},"100819004":{"id_estudiante":"100819004","matricula":"100819004","nombre":"Ortiz Nuñez, Lorena"},"100820570":{"id_estudiante":"100820570","matricula":"100820570","nombre":"Betances De Los Santos, Nissi"},"100820712":{"id_estudiante":"100820712","matricula":"100820712","nombre":"Fermin Encarnacion, Esmaylin"},"AG7787":{"id_estudiante":"AG7787","matricula":"AG7787","nombre":"Perez Gonzalez, Yeceline"},"DC6387":{"id_estudiante":"DC6387","matricula":"DC6387","nombre":"Sandoval A, Patricia"}},"evaluaciones":{"-Ok98dhdH7J6D_Z2pLrl":{"esExtra":1,"id":"-Ok98dhdH7J6D_Z2pLrl","nombre":"PUNTOS EXTRA","valor":100},"-Oo5U39jeoht0qJuAcsl":{"esExtra":0,"id":"-Oo5U39jeoht0qJuAcsl","nombre":"Manual parte 1","valor":8}},"notas":{"-Ok98dhdH7J6D_Z2pLrl":{"100167064":4.5,"100307602":2,"100582172":5.5,"100608514":1,"100719477":2,"100719914":2,"100750864":0.5,"100756188":4,"100763031":2,"100783066":2,"100807586":6,"100812085":1.5,"100817106":2,"100817878":4.5,"100818029":2,"100818301":5.5,"100818304":2,"100818935":3.5,"100818944":2,"100819002":2.5,"100820570":2.5,"100820712":2,"AG7787":2},"-Oo5U39jeoht0qJuAcsl":{"100167064":8,"100582172":8,"100719477":8,"100719914":7.5,"100750864":6.5,"100756188":8,"100803815":8,"100807586":8,"100808575":6,"100810270":5,"100817106":6.5,"100817878":8,"100818029":8,"100818301":8,"100818304":8,"100818944":8,"100819002":8,"100820570":8,"100820712":6.5,"AG7787":8,"DC6387":7.5}}},"33401":{"encuentros":{"e0":{"aula":"LABORATORIO DE FISICA - SEDE 211","dias":"V","hora":"1:00 PM - 3:50 PM"}},"estudiantes":{"100115384":{"id_estudiante":"100115384","matricula":"100115384","nombre":"Mateo Lara, Paula"},"100140817":{"id_estudiante":"100140817","matricula":"100140817","nombre":"Mora De La Rosa, Rosa I."},"100544571":{"id_estudiante":"100544571","matricula":"100544571","nombre":"Lorenzo Terrero, Rony"},"100558106":{"id_estudiante":"100558106","matricula":"100558106","nombre":"Cordero De Los Santos, Daniela"},"100564066":{"id_estudiante":"100564066","matricula":"100564066","nombre":"Orbe Marquez, Roberto Angel"},"100633199":{"id_estudiante":"100633199","matricula":"100633199","nombre":"Mendez Moronta, Denis Laurelis"},"100636623":{"id_estudiante":"100636623","matricula":"100636623","nombre":"Peña Baldera, Marian Yasmilka"},"100686277":{"id_estudiante":"100686277","matricula":"100686277","nombre":"Cueva Valdez, Yoangela"},"100694401":{"id_estudiante":"100694401","matricula":"100694401","nombre":"De Los Santos Aristy, Lisbeth Clary"},"100704981":{"id_estudiante":"100704981","matricula":"100704981","nombre":"Cedeño Florentino, Yokasta"},"100719208":{"id_estudiante":"100719208","matricula":"100719208","nombre":"Montero Quezada, Ana Paola"},"100719639":{"id_estudiante":"100719639","matricula":"100719639","nombre":"De La Cruz Gonzalez, Rachel"},"100722983":{"id_estudiante":"100722983","matricula":"100722983","nombre":"Frias Aguero, Steisy Dahiana"},"100725706":{"id_estudiante":"100725706","matricula":"100725706","nombre":"Encarnacion Alcantara, Treisy Genezareth"},"100738620":{"id_estudiante":"100738620","matricula":"100738620","nombre":"Reyes Ventura, Jose Armando"},"100742256":{"id_estudiante":"100742256","matricula":"100742256","nombre":"Frias, Astrit Carolina"},"100745222":{"id_estudiante":"100745222","matricula":"100745222","nombre":"Garcia Jerez, Elizabeth"},"100750760":{"id_estudiante":"100750760","matricula":"100750760","nombre":"De Jesus Guerrero, Esmailyn Yessenia"},"100763870":{"id_estudiante":"100763870","matricula":"100763870","nombre":"Rodriguez Nivar, Alexandra"},"100764240":{"id_estudiante":"100764240","matricula":"100764240","nombre":"Javier Peña, Luis   David"},"100769854":{"id_estudiante":"100769854","matricula":"100769854","nombre":"Santana Velez, Jufreisy"},"100779427":{"id_estudiante":"100779427","matricula":"100779427","nombre":"Taveras Liranzo, Florangel"},"100779486":{"id_estudiante":"100779486","matricula":"100779486","nombre":"Almonte         Miguel, Francisca"},"100780048":{"id_estudiante":"100780048","matricula":"100780048","nombre":"Torres Pichardo, Derian"},"100784357":{"id_estudiante":"100784357","matricula":"100784357","nombre":"Guerrero Pimentel, Dalia"},"100784451":{"id_estudiante":"100784451","matricula":"100784451","nombre":"Martinez Marte, Ismeyrin Melissa"},"100785367":{"id_estudiante":"100785367","matricula":"100785367","nombre":"Cruz De Jesus, Carolina"},"100785809":{"id_estudiante":"100785809","matricula":"100785809","nombre":"Nova Vicioso, Yasmel"},"100786432":{"id_estudiante":"100786432","matricula":"100786432","nombre":"Francisco Rodriguez, Ana Maria"},"100789480":{"id_estudiante":"100789480","matricula":"100789480","nombre":"Diaz Garcia, Crismeily"},"100789857":{"id_estudiante":"100789857","matricula":"100789857","nombre":"Severino Florentino, Yuly Michelle"},"100791032":{"id_estudiante":"100791032","matricula":"100791032","nombre":"Gil Victoriano, Yameily `"},"100794323":{"id_estudiante":"100794323","matricula":"100794323","nombre":"Amador Vicente, Jeferson"},"100801602":{"id_estudiante":"100801602","matricula":"100801602","nombre":"Dipre Reyes, Viady"},"100806518":{"id_estudiante":"100806518","matricula":"100806518","nombre":"Melo Mejia, Yuleica Beronica"},"100807513":{"id_estudiante":"100807513","matricula":"100807513","nombre":"Alcantara Ortiz, Slanni Yhonaisi"},"100810103":{"id_estudiante":"100810103","matricula":"100810103","nombre":"Estrella Baez, Joseph Gabriel"},"100811193":{"id_estudiante":"100811193","matricula":"100811193","nombre":"Mateo Mojica, Ivan Miguel"},"100818185":{"id_estudiante":"100818185","matricula":"100818185","nombre":"Zorrilla Matos, Alejandra"},"100819122":{"id_estudiante":"100819122","matricula":"100819122","nombre":"Contreras Baez, Hanpherny"},"100819440":{"id_estudiante":"100819440","matricula":"100819440","nombre":"Sanchez, Alanna Zamira"},"100819702":{"id_estudiante":"100819702","matricula":"100819702","nombre":"Vasquez Mirabal, Yadailis Nayae"},"100821333":{"id_estudiante":"100821333","matricula":"100821333","nombre":"Lopez Familia, Maria Elisa"},"100821390":{"id_estudiante":"100821390","matricula":"100821390","nombre":"Mendoza Ramirez, Anyelina"},"100821467":{"id_estudiante":"100821467","matricula":"100821467","nombre":"Perez Liberato, Alina Esmeralda"},"100822010":{"id_estudiante":"100822010","matricula":"100822010","nombre":"Oviedo, Leamny Celeste"}},"evaluaciones":{"-OkF1GcMGUjYdBYVmkVA":{"esExtra":1,"id":"-OkF1GcMGUjYdBYVmkVA","nombre":"PUNTOS EXTRA","valor":100},"-OoBIC8DAnA3pl3eVhx8":{"esExtra":0,"id":"-OoBIC8DAnA3pl3eVhx8","nombre":"Manual parte 1","valor":8}},"notas":{"-OkF1GcMGUjYdBYVmkVA":{"100725706":1,"100780048":1,"100789480":3,"100807513":1,"100810103":0.5,"100811193":4,"100818185":1,"100819440":2,"100819702":0.5,"100821333":1.5,"100821467":0.5},"-OoBIC8DAnA3pl3eVhx8":{"100140817":8,"100722983":7,"100738620":4.5,"100764240":6.5,"100780048":8,"100784357":7,"100785809":7,"100789480":8,"100791032":8,"100801602":3,"100807513":8,"100810103":6,"100811193":8,"100818185":8,"100819122":3.5,"100819440":7.5,"100819702":8,"100821333":8,"100821467":4.5,"100822010":4.5}}},"33847":{"encuentros":{"e0":{"aula":"FACULTAD DE INGENIERIA 216","dias":"M","hora":"8:00 PM - 9:50 PM"}},"estudiantes":{"977310":{"id_estudiante":"977310","matricula":"977310","nombre":"Jimenez Bello, Miguel"},"100150862":{"id_estudiante":"100150862","matricula":"100150862","nombre":"Pineda Reyes, Juan C."},"100270817":{"id_estudiante":"100270817","matricula":"100270817","nombre":"Montero Santos, Angel Miguel"},"100270878":{"id_estudiante":"100270878","matricula":"100270878","nombre":"Nuñez Sosa, Josue"},"100304137":{"id_estudiante":"100304137","matricula":"100304137","nombre":"Montilla Hernandez, Joel Adonis"},"100330891":{"id_estudiante":"100330891","matricula":"100330891","nombre":"Amador Alcantara, Johan Manuel"},"100389557":{"id_estudiante":"100389557","matricula":"100389557","nombre":"Batista, Gerson"},"100391882":{"id_estudiante":"100391882","matricula":"100391882","nombre":"Encarnacion Rivera, Gilbert"},"100412648":{"id_estudiante":"100412648","matricula":"100412648","nombre":"Vasquez Encarnacion, Jose Emiliano"},"100484847":{"id_estudiante":"100484847","matricula":"100484847","nombre":"Martinez Ortiz, Luis Ernesto"},"100488327":{"id_estudiante":"100488327","matricula":"100488327","nombre":"Peña Lara, Ismael"},"100499532":{"id_estudiante":"100499532","matricula":"100499532","nombre":"Montero Toribio, Lewin Tomas"},"100501860":{"id_estudiante":"100501860","matricula":"100501860","nombre":"Soto Mateo, Leslie Yamileth"},"100532964":{"id_estudiante":"100532964","matricula":"100532964","nombre":"Hinojosa Boyer, Miguel Jose"},"100551821":{"id_estudiante":"100551821","matricula":"100551821","nombre":"Muñoz Cuevas, Ana Maria"},"100566835":{"id_estudiante":"100566835","matricula":"100566835","nombre":"Sanchez Morillo, Raquel"},"100582808":{"id_estudiante":"100582808","matricula":"100582808","nombre":"Salgado Jorge, Emely"},"100585982":{"id_estudiante":"100585982","matricula":"100585982","nombre":"Diaz Mota, Eliel David"},"100590556":{"id_estudiante":"100590556","matricula":"100590556","nombre":"Lizardo Baez, Karen Maria"},"100620639":{"id_estudiante":"100620639","matricula":"100620639","nombre":"Mateo Novas, Andreina"},"100623226":{"id_estudiante":"100623226","matricula":"100623226","nombre":"Alcantara Mendez, Elianny Grismeylin"},"100632228":{"id_estudiante":"100632228","matricula":"100632228","nombre":"Roa Turbi, Paola Franchesca"},"100674610":{"id_estudiante":"100674610","matricula":"100674610","nombre":"Garcia Rodriguez, Wilman"},"100699924":{"id_estudiante":"100699924","matricula":"100699924","nombre":"Gomez Matos, Joel"},"100701856":{"id_estudiante":"100701856","matricula":"100701856","nombre":"Tavarez Tejeda, Joan Manuel"},"100702386":{"id_estudiante":"100702386","matricula":"100702386","nombre":"Cuevas Tejeda, Norbert"},"100734426":{"id_estudiante":"100734426","matricula":"100734426","nombre":"Viguera Martinez, Keyri Jeannette"},"100770180":{"id_estudiante":"100770180","matricula":"100770180","nombre":"Baez Feliz, Brailyn Esmil"},"100778820":{"id_estudiante":"100778820","matricula":"100778820","nombre":"Ramirez Ramirez, Eliana Elisbeth"},"100779451":{"id_estudiante":"100779451","matricula":"100779451","nombre":"Vallejo Herrera, Keiner Antonio"}},"evaluaciones":{"-Oka2-bSlcEKUL0M_0cM":{"esExtra":1,"id":"-Oka2-bSlcEKUL0M_0cM","nombre":"PUNTOS EXTRA","valor":100},"-OnqYowWp-2jHuc_HNFd":{"esExtra":0,"id":"-OnqYowWp-2jHuc_HNFd","nombre":"1er parcial","valor":25}},"notas":{"-Oka2-bSlcEKUL0M_0cM":{"100412648":0.5,"100488327":0.5,"100532964":0.5,"100734426":2}}},"40041":{"asistencia_datos":{"-Ol2egnbkDhoPH1ctDYL":{"100234543":true,"100419405":true,"100610516":true,"100612799":true,"100662852":true,"100671633":true,"100692205":true,"100718377":true,"100720471":true,"100751594":true,"100774913":true,"100780975":true,"100784857":true,"100788915":true,"100790655":true,"100794507":true,"100808053":true,"100809229":true,"100812781":true,"100813415":true,"100817807":true,"100818639":true,"100820567":true,"100821407":true,"100823723":true,"100824328":true,"DB6153":true,"DB6437":true}},"asistencias":{"-Ol2egnbkDhoPH1ctDYL":{"fecha":"2026-02-09","id":"-Ol2egnbkDhoPH1ctDYL","nombre":"2026-02-09"}},"encuentros":{"e0":{"aula":"LABORATORIO DE FISICA - SEDE 213","dias":"L","hora":"1:00 PM - 3:50 PM"}},"estudiantes":{"100234543":{"id_estudiante":"100234543","matricula":"100234543","nombre":"Rodriguez Perez, Yohani"},"100419405":{"id_estudiante":"100419405","matricula":"100419405","nombre":"Rodriguez Perez, Edita"},"100452917":{"id_estudiante":"100452917","matricula":"100452917","nombre":"Matos Cuevas, Denys Paola"},"100471141":{"id_estudiante":"100471141","matricula":"100471141","nombre":"Mauricio Berroa, Yosiris"},"100610516":{"id_estudiante":"100610516","matricula":"100610516","nombre":"Rivera Meran, Maribel"},"100612799":{"id_estudiante":"100612799","matricula":"100612799","nombre":"Silverio Green, Juan Carlos"},"100645824":{"id_estudiante":"100645824","matricula":"100645824","nombre":"Brito Morey, Julio Cesar"},"100662852":{"id_estudiante":"100662852","matricula":"100662852","nombre":"Nuñez Achil, Leonora Escarla"},"100671633":{"id_estudiante":"100671633","matricula":"100671633","nombre":"Valerio Jimenez, Reylon Baldes"},"100686635":{"id_estudiante":"100686635","matricula":"100686635","nombre":"Arias, Franyeli"},"100692205":{"id_estudiante":"100692205","matricula":"100692205","nombre":"Frometa Diaz, Ricarly"},"100695134":{"id_estudiante":"100695134","matricula":"100695134","nombre":"Paulino, Yineiri"},"100698537":{"id_estudiante":"100698537","matricula":"100698537","nombre":"Payano Familia, Darlwin Alberto"},"100706791":{"id_estudiante":"100706791","matricula":"100706791","nombre":"De Paula Lugo, Alfonso"},"100718377":{"id_estudiante":"100718377","matricula":"100718377","nombre":"Fernandez Soriano, Arlenys"},"100720471":{"id_estudiante":"100720471","matricula":"100720471","nombre":"Hernandez Victoriano, Achely"},"100720708":{"id_estudiante":"100720708","matricula":"100720708","nombre":"Reyes Sena, Cesiah Elizabeth"},"100745535":{"id_estudiante":"100745535","matricula":"100745535","nombre":"Read Arache, Paul Fitzgerald"},"100751594":{"id_estudiante":"100751594","matricula":"100751594","nombre":"Rosario Berroa, Victor  Daniel"},"100751827":{"id_estudiante":"100751827","matricula":"100751827","nombre":"Abreu Javier, Leudy Porfirio"},"100761164":{"id_estudiante":"100761164","matricula":"100761164","nombre":"Garcia Encarnacion, Ana Yoleidy"},"100774913":{"id_estudiante":"100774913","matricula":"100774913","nombre":"Jose Dipre, Josue"},"100775412":{"id_estudiante":"100775412","matricula":"100775412","nombre":"Ramirez Jimenez, Mia Elizabeth"},"100780975":{"id_estudiante":"100780975","matricula":"100780975","nombre":"Herrera Guzman, Francina"},"100783851":{"id_estudiante":"100783851","matricula":"100783851","nombre":"Matos Garcia, Mauren"},"100784857":{"id_estudiante":"100784857","matricula":"100784857","nombre":"Encarnacion Peñalo, Jualisa Lucero"},"100786262":{"id_estudiante":"100786262","matricula":"100786262","nombre":"Cid Nova, Dixon Asbel"},"100788915":{"id_estudiante":"100788915","matricula":"100788915","nombre":"Ortega Concepcion, Darleny"},"100789487":{"id_estudiante":"100789487","matricula":"100789487","nombre":"Diaz Salas, Rufina"},"100790655":{"id_estudiante":"100790655","matricula":"100790655","nombre":"Gil Grullon, Luisanna Miguelina"},"100794507":{"id_estudiante":"100794507","matricula":"100794507","nombre":"Canario Jimenez, Noelis"},"100803101":{"id_estudiante":"100803101","matricula":"100803101","nombre":"De Jesus De Aza, Ricardo Tomas"},"100808053":{"id_estudiante":"100808053","matricula":"100808053","nombre":"Lebron Alcequiez, Alanna Michelle"},"100809229":{"id_estudiante":"100809229","matricula":"100809229","nombre":"Henriquez Almonte, Ashley Shamar"},"100812781":{"id_estudiante":"100812781","matricula":"100812781","nombre":"Marte Pierre, Juan Pablo"},"100813415":{"id_estudiante":"100813415","matricula":"100813415","nombre":"Suarez De La Cruz, Nehrumie Elias"},"100817807":{"id_estudiante":"100817807","matricula":"100817807","nombre":"Abreu Gil, Anyelina Griselis"},"100818639":{"id_estudiante":"100818639","matricula":"100818639","nombre":"Nivar Parra, Harolly Camila"},"100819126":{"id_estudiante":"100819126","matricula":"100819126","nombre":"Cordero Lorenzo, Algelys"},"100820567":{"id_estudiante":"100820567","matricula":"100820567","nombre":"Benual Vasquez, Lia Marie"},"100821407":{"id_estudiante":"100821407","matricula":"100821407","nombre":"Mora Veloz, Mayelin"},"100823723":{"id_estudiante":"100823723","matricula":"100823723","nombre":"Arroyo Peña, Sherley Marie"},"100824328":{"id_estudiante":"100824328","matricula":"100824328","nombre":"Rodriguez Vizcaino, Frainy"},"DB6153":{"id_estudiante":"DB6153","matricula":"DB6153","nombre":"Moni Eusebio, Sujeidy"},"DB6437":{"id_estudiante":"DB6437","matricula":"DB6437","nombre":"Vasquez R, Greysi"}},"evaluaciones":{"-OkULmIMTyGCmpI_070S":{"esExtra":1,"id":"-OkULmIMTyGCmpI_070S","nombre":"PUNTOS EXTRA","valor":100},"-OnrfSKQLGihecoXVUby":{"esExtra":0,"id":"-OnrfSKQLGihecoXVUby","nombre":"Manual parte 1","valor":8},"-OoQSz9qfl7261VhDJ_F":{"esExtra":0,"id":"-OoQSz9qfl7261VhDJ_F","nombre":"1er parcial","valor":25}},"historial_dictados":{"-OoQSz9qfl7261VhDJ_F":{"2026-03-23T23-31-27-035Z":{"100612799":17,"100671633":2,"100718377":6,"100751594":7,"100780975":3,"100788915":6.5,"100794507":16,"100808053":13,"100809229":24,"100812781":17.5,"100813415":18,"100818639":2,"100820567":10.5,"100821407":4,"100823723":4,"DB6153":10.5,"DB6437":4}}},"notas":{"-OkULmIMTyGCmpI_070S":{"100234543":0.5,"100610516":0.5,"100612799":3,"100645824":0.5,"100671633":1,"100720471":0.5,"100780975":0.5,"100786262":1.5,"100788915":1.5,"100808053":4,"100809229":2.5,"100812781":4,"100813415":1.5,"100817807":1.5,"100818639":0.5,"100820567":1.5,"100823723":1,"DB6153":2,"DB6437":0.5},"-OnrfSKQLGihecoXVUby":{"100612799":8,"100718377":7.5,"100720471":8,"100751594":8,"100780975":8,"100788915":8,"100794507":8,"100808053":8,"100809229":8,"100812781":5,"100813415":8,"100818639":8,"100820567":8,"100821407":8,"100823723":8,"DB6153":8},"-OoQSz9qfl7261VhDJ_F":{"100612799":17,"100671633":2,"100718377":6,"100720471":"12","100751594":7,"100780975":3,"100788915":6.5,"100794507":16,"100808053":13,"100809229":24,"100812781":17.5,"100813415":18,"100818639":2,"100820567":10.5,"100821407":4,"100823723":4,"DB6153":10.5,"DB6437":4}}}}